agentscale/__init__.py
agentscale-0.1.0.dist-info/WHEEL
agentscale-0.1.0.dist-info/entry_points.txt
agentscale-0.1.0.dist-info/METADATA
agentscale-0.1.0.dist-info/RECORD
