Metadata-Version: 2.3
Name: agentscale
Version: 0.1.0
Summary: AgentScale an open source control plane for generative AI agents
Author: Qiulin Li
Author-email: Qiulin Li <liqiulin@outlook.com>
Requires-Python: >=3.13
